frog-api/__init__.py
frog-api/frog.py
frog-api/tool.py
src/__init__.py
src/frog.py
src/tool.py
frog_api-0.1.0.dist-info/METADATA
frog_api-0.1.0.dist-info/WHEEL
frog_api-0.1.0.dist-info/entry_points.txt
frog_api-0.1.0.dist-info/top_level.txt
frog_api-0.1.0.dist-info/RECORD
