Metadata-Version: 2.1
Name: frog-api
Version: 0.1.0
Summary: sample wsgi server
Author: smart_long
Author-email: smart_long@outlook.com
License: MIT
Classifier: Programming Language :: Python :: 3.10
Classifier: Programming Language :: Python :: 3.9
Classifier: Programming Language :: Python :: 3.8
Requires-Dist: urllib3 ==1.26.15
Requires-Dist: Click
Requires-Dist: pymysql
Requires-Dist: peewee
Requires-Dist: peewee-migrate
Requires-Dist: PyJWT
Requires-Dist: pycryptodome
Requires-Dist: xmldict
